odoo/addons/mail_activity_mail_template/CHANGELOG.md
odoo/addons/mail_activity_mail_template/README.rst
odoo/addons/mail_activity_mail_template/__init__.py
odoo/addons/mail_activity_mail_template/__manifest__.py
odoo/addons/mail_activity_mail_template/demo/mail_activity_type.xml
odoo/addons/mail_activity_mail_template/demo/mail_template.xml
odoo/addons/mail_activity_mail_template/models/__init__.py
odoo/addons/mail_activity_mail_template/models/mail_activity.py
odoo/addons/mail_activity_mail_template/static/description/icon.png
odoo/addons/mail_activity_mail_template/tests/__init__.py
odoo/addons/mail_activity_mail_template/tests/test_mail_activity.py
odoo/addons/mail_activity_mail_template/views/mail_activity_view.xml
odoo12_addon_mail_activity_mail_template-12.0.0.1.1.dist-info/METADATA
odoo12_addon_mail_activity_mail_template-12.0.0.1.1.dist-info/WHEEL
odoo12_addon_mail_activity_mail_template-12.0.0.1.1.dist-info/top_level.txt
odoo12_addon_mail_activity_mail_template-12.0.0.1.1.dist-info/RECORD
